pychub/__init__.py
pychub/model/__init__.py
pychub/model/chubconfig_model.py
pychub/model/chubproject_model.py
pychub/model/dataclass_shim.py
pychub/model/includes_model.py
pychub/model/scripts_model.py
pychub/model/wheelinfo_model.py
pychub/package/__init__.py
pychub/package/bt_options_processor.py
pychub/package/chubproject.py
pychub/package/cli.py
pychub/package/constants.py
pychub/package/packager.py
pychub/runtime/__init__.py
pychub/runtime/__main__.py
pychub/runtime/actions/__init__.py
pychub/runtime/actions/chubconfig.py
pychub/runtime/actions/discover.py
pychub/runtime/actions/entrypoint.py
pychub/runtime/actions/install.py
pychub/runtime/actions/install_hooks.py
pychub/runtime/actions/list.py
pychub/runtime/actions/runtime_main.py
pychub/runtime/actions/unpack.py
pychub/runtime/actions/venv.py
pychub/runtime/actions/version.py
pychub/runtime/cli.py
pychub/runtime/constants.py
pychub/runtime/rt_options_processor.py
pychub/runtime/utils.py
pychub-1.1.1.dist-info/METADATA
pychub-1.1.1.dist-info/WHEEL
pychub-1.1.1.dist-info/entry_points.txt
pychub-1.1.1.dist-info/licenses/LICENSE
pychub-1.1.1.dist-info/RECORD
