Metadata-Version: 2.4
Name: pychub
Version: 1.1.1
Summary: Make a Python-native .chub installer from wheels and their dependencies.
License: Copyright 2025 Steve Storck <steve973@gmail.com>
License-File: LICENSE
Keywords: bundle,chub,executable,package,packaging,zipapp
Author: Steve Storck
Author-email: steve973@gmail.com
Requires-Python: >=3.9,<4.0
Classifier: Development Status :: 4 - Beta
Classifier: Environment :: Console
Classifier: Intended Audience :: Developers
Classifier: Operating System :: Unix
Classifier: Operating System :: POSIX :: Linux
Classifier: Operating System :: MacOS :: MacOS X
Classifier: Programming Language :: Python
Classifier: Programming Language :: Python :: 3
Classifier: Programming Language :: Python :: 3 :: Only
Classifier: Programming Language :: Python :: 3.9
Classifier: Programming Language :: Python :: 3.10
Classifier: Programming Language :: Python :: 3.11
Classifier: Programming Language :: Python :: 3.12
Classifier: Programming Language :: Python :: 3.13
Classifier: Programming Language :: Python :: 3.14
Classifier: Topic :: System :: Archiving :: Packaging
Classifier: Topic :: System :: Installation/Setup
Classifier: Topic :: System :: Software Distribution
Classifier: Topic :: Utilities
Requires-Dist: attrs (>=25.3.0)
Requires-Dist: pyyaml (>=6.0.3)
Requires-Dist: tomli (>=2.2) ; python_version < "3.11"
Requires-Dist: tomli-w (>=1.2.0)
Project-URL: Homepage, https://github.com/Steve973/pychub
Project-URL: Source, https://github.com/Steve973/pychub/tree/main
